{
  "0.66.3": 2239,
  "0.62.22": 9278,
  "0.63.41": 980,
  "0.64.25": 276,
  "0.61.16": 156,
  "0.59.0-vnext.208": 3,
  "0.65.7": 143,
  "0.67.0-preview.1": 116,
  "0.0.0-canary.412": 156,
  "0.0.0-canary.411": 267,
  "0.0.0-canary.410": 191,
  "0.0.0-canary.409": 104,
  "0.0.0-canary.408": 17,
  "0.0.0-canary.407": 12,
  "0.66.2": 2296,
  "0.64.24": 16,
  "0.0.0-canary.406": 9,
  "0.0.0-canary.405": 11,
  "0.0.0-canary.404": 6,
  "0.0.0-canary.403": 6,
  "0.0.0-canary.402": 6,
  "0.0.0-canary.401": 3,
  "0.65.6": 59,
  "0.66.1": 451,
  "0.64.23": 117,
  "0.0.0-canary.400": 3,
  "0.0.0-canary.399": 3,
  "0.0.0-canary.398": 1,
  "0.0.0-canary.397": 1,
  "0.64.22": 4,
  "0.0.0-canary.396": 4,
  "0.0.0-canary.395": 1,
  "0.66.0": 29,
  "0.65.5": 50,
  "0.64.21": 4,
  "0.0.0-canary.394": 3,
  "0.0.0-canary.393": 2,
  "0.0.0-canary.392": 2,
  "0.0.0-canary.391": 1,
  "0.66.0-preview.6": 2,
  "0.65.4": 143,
  "0.64.20": 5,
  "0.0.0-canary.390": 1,
  "0.0.0-canary.389": 1,
  "0.0.0-canary.388": 1,
  "0.63.40": 6,
  "0.0.0-canary.387": 1,
  "0.0.0-canary.386": 1,
  "0.0.0-canary.385": 1,
  "0.66.0-preview.5": 3,
  "0.65.3": 146,
  "0.64.19": 4,
  "0.63.39": 13,
  "0.0.0-canary.384": 1,
  "0.0.0-canary.383": 1,
  "0.0.0-canary.382": 1,
  "0.63.38": 4,
  "0.0.0-canary.381": 2,
  "0.0.0-canary.380": 1,
  "0.66.0-preview.4": 3,
  "0.0.0-canary.379": 1,
  "0.0.0-canary.378": 1,
  "0.0.0-canary.377": 2,
  "0.0.0-canary.376": 1,
  "0.0.0-canary.375": 1,
  "0.66.0-preview.3": 2,
  "0.64.18": 22,
  "0.0.0-canary.374": 1,
  "0.0.0-canary.373": 1,
  "0.0.0-canary.372": 2,
  "0.0.0-canary.371": 1,
  "0.65.2": 692,
  "0.66.0-preview.2": 1,
  "0.64.17": 4,
  "0.0.0-canary.370": 2,
  "0.66.0-preview.1": 1,
  "0.0.0-canary.367": 1,
  "0.64.16": 32,
  "0.65.1": 102,
  "0.0.0-canary.366": 1,
  "0.63.37": 475,
  "0.64.15": 43,
  "0.65.0": 3289,
  "0.0.0-canary.363": 1,
  "0.0.0-canary.362": 2,
  "0.0.0-canary.360": 1,
  "0.65.0-preview.8": 1,
  "0.0.0-canary.356": 1,
  "0.0.0-canary.352": 2,
  "0.0.0-canary.351": 1,
  "0.0.0-canary.350": 1,
  "0.65.0-preview.7": 1,
  "0.65.0-preview.6": 1,
  "0.64.14": 4431,
  "0.64.13": 23,
  "0.65.0-preview.5": 1,
  "0.65.0-preview.4": 1,
  "0.0.0-canary.336": 1,
  "0.63.36": 4169,
  "0.64.12": 44,
  "0.65.0-preview.3": 1,
  "0.63.35": 38,
  "0.63.34": 70,
  "0.63.33": 5,
  "0.0.0-canary.322": 2,
  "0.64.11": 193,
  "0.65.0-preview.2": 1,
  "0.63.32": 112,
  "0.64.10": 54,
  "0.63.31": 2,
  "0.64.9": 14,
  "0.63.30": 51,
  "0.64.8": 10,
  "0.63.29": 2,
  "0.0.0-canary.312": 1,
  "0.63.28": 4,
  "0.64.7": 12,
  "0.0.0-canary.307": 3,
  "0.0.0-canary.305": 1,
  "0.0.0-canary.303": 1,
  "0.64.6": 12,
  "0.0.0-canary.302": 1,
  "0.0.0-canary.301": 1,
  "0.0.0-canary.299": 1,
  "0.0.0-canary.298": 1,
  "0.64.5": 182,
  "0.0.0-canary.294": 1,
  "0.64.4": 3,
  "0.0.0-canary.292": 1,
  "0.0.0-canary.291": 1,
  "0.0.0-canary.290": 1,
  "0.63.27": 3197,
  "0.0.0-canary.286": 2,
  "0.64.3": 87,
  "0.64.2": 81,
  "0.63.26": 30,
  "0.0.0-canary.281": 1,
  "0.0.0-canary.279": 1,
  "0.64.1": 241,
  "0.0.0-canary.278": 1,
  "0.64.0": 14,
  "0.0.0-canary.273": 2,
  "0.64.0-preview.15": 3,
  "0.64.0-preview.14": 5,
  "0.63.24": 9,
  "0.0.0-canary.267": 1,
  "0.0.0-canary.265": 1,
  "0.63.23": 117,
  "0.64.0-preview.13": 1,
  "0.0.0-canary.260": 1,
  "0.64.0-preview.12": 2,
  "0.63.22": 176,
  "0.64.0-preview.11": 1,
  "0.63.21": 1,
  "0.64.0-preview.10": 1,
  "0.0.0-canary.249": 1,
  "0.64.0-preview.9": 1,
  "0.63.20": 28,
  "0.0.0-canary.246": 1,
  "0.63.19": 5,
  "0.64.0-preview.8": 1,
  "0.63.18": 11,
  "0.64.0-preview.7": 1,
  "0.0.0-canary.234": 1,
  "0.62.21": 324,
  "0.63.17": 18,
  "0.64.0-preview.6": 1,
  "0.64.0-preview.5": 1,
  "0.63.16": 62,
  "0.0.0-canary.229": 1,
  "0.62.20": 93,
  "0.62.19": 5,
  "0.63.15": 73,
  "0.64.0-preview.4": 1,
  "0.64.0-preview.3": 1,
  "0.63.14": 2,
  "0.63.13": 26,
  "0.62.18": 170,
  "0.0.0-canary.222": 1,
  "0.64.0-preview.2": 1,
  "0.0.0-canary.221": 1,
  "0.64.0-preview.1": 1,
  "0.0.0-canary.219": 1,
  "0.63.11": 5,
  "0.62.17": 1105,
  "0.0.0-canary.216": 1,
  "0.0.0-canary.211": 1,
  "0.63.10": 19,
  "0.0.0-canary.210": 1,
  "0.0.0-canary.208": 1,
  "0.62.16": 87,
  "0.0.0-canary.206": 1,
  "0.0.0-canary.203": 1,
  "0.62.15": 64,
  "0.63.6": 75,
  "0.0.0-canary.193": 1,
  "0.0.0-canary.189": 1,
  "0.62.14": 117,
  "0.0.0-canary.188": 1,
  "0.0.0-canary.184": 1,
  "0.62.13": 30,
  "0.0.0-canary.183": 1,
  "0.63.5": 85,
  "0.63.4": 2,
  "0.0.0-canary.172": 1,
  "0.62.12": 437,
  "0.62.11": 63,
  "0.63.3": 230,
  "0.62.10": 30,
  "0.63.2": 13,
  "0.62.9": 21,
  "0.63.1": 6,
  "0.62.7": 47,
  "0.63.0": 5,
  "0.63.0-preview.5": 1,
  "0.62.6": 664,
  "0.63.0-preview.4": 1,
  "0.62.5": 89,
  "0.61.15": 18,
  "0.63.0-preview.3": 1,
  "0.63.0-preview.2": 2,
  "0.62.4": 252,
  "0.63.0-preview.1": 1,
  "0.0.0-canary.133": 1,
  "0.62.3": 82,
  "0.0.0-canary.127": 1,
  "0.62.2": 202,
  "0.62.1": 220,
  "0.62.0": 334,
  "0.62.0-preview.17": 4,
  "0.61.14": 1,
  "0.0.0-canary.96": 37,
  "0.0.0-canary.95": 2,
  "0.62.0-preview.16": 12,
  "0.62.0-preview.15": 6,
  "0.62.0-preview.14": 3,
  "0.62.0-preview.13": 1,
  "0.0.0-master.91": 1,
  "0.62.0-preview.12": 1,
  "0.62.0-preview.11": 1,
  "0.62.0-preview.10": 1,
  "0.62.0-preview.9": 1,
  "0.62.0-preview.8": 2,
  "0.60.0-vnext.167": 1,
  "0.62.0-preview.7": 1,
  "0.0.0-master.69": 1,
  "0.0.0-master.67": 1,
  "0.62.0-preview.6": 49,
  "0.0.0-master.66": 1,
  "0.62.0-preview.5": 1,
  "0.62.0-preview.4": 1,
  "0.61.9": 20,
  "0.62.0-preview.3": 1,
  "0.0.0-master.60": 1,
  "0.61.8": 49,
  "0.62.0-preview.2": 1,
  "0.62.0-preview.1": 1,
  "0.0.0-master.45": 1,
  "0.0.0-master.39": 1,
  "0.0.0-master.23": 1,
  "0.0.0-master.17": 1,
  "0.61.2": 1,
  "0.61.0": 280,
  "0.61.0-beta.60": 144,
  "0.61.0-beta.58": 27,
  "0.60.0-vnext.110": 3,
  "0.60.0-vnext.95": 3,
  "0.59.0-legacy.2": 6,
  "0.59.0-legacy.1": 23,
  "0.60.0-vnext.77": 219,
  "0.60.0-vnext.67": 1,
  "0.60.0-vnext.63": 1,
  "0.59.0-rc.5": 1,
  "0.60.0-vnext.54": 1,
  "0.60.0-vnext.51": 1,
  "0.60.0-vnext.47": 1,
  "0.60.0-vnext.46": 1,
  "0.60.0-vnext.39": 1,
  "0.60.0-vnext.36": 1,
  "0.60.0-vnext.35": 1,
  "0.60.0-vnext.30": 1,
  "0.60.0-vnext.18": 1,
  "0.59.0-vnext.195": 1,
  "0.59.0-vnext.194": 1,
  "0.60.0-vnext.5": 1,
  "0.59.0-vnext.184": 1,
  "0.59.0-vnext.179": 1,
  "0.59.0-vnext.178": 1,
  "0.59.0-vnext.177": 1,
  "0.59.0-vnext.167": 1,
  "0.59.0-vnext.166": 1,
  "0.59.0-vnext.156": 1,
  "0.59.0-vnext.153": 1,
  "0.59.0-rc.3": 14,
  "0.59.0-vnext.131": 1,
  "0.55.0-rc.1": 1,
  "0.59.0-rc.1": 1,
  "0.59.0-vnext.92": 1,
  "0.59.0-vnext.75": 1,
  "0.59.0-vnext.70": 1,
  "0.59.0-vnext.56": 1,
  "0.59.0-vnext.49": 2,
  "0.59.0-vnext.46": 1,
  "0.59.0-vnext.45": 1,
  "0.59.0-vnext.32": 1,
  "0.59.0-vnext.18": 1,
  "0.59.0-vnext.15": 1,
  "0.59.0-vnext.11": 1,
  "0.58.0-vnext.167": 1,
  "0.58.0-vnext.159": 1,
  "0.58.0-vnext.154": 1,
  "0.58.0-vnext.153": 1,
  "0.57.2": 48,
  "0.58.0-vnext.151": 1,
  "0.58.0-vnext.145": 1,
  "0.58.0-vnext.144": 1,
  "0.58.0-vnext.143": 1,
  "0.58.0-vnext.142": 1,
  "0.58.0-vnext.141": 1,
  "0.58.0-vnext.140": 1,
  "0.58.0-vnext.139": 1,
  "0.58.0-vnext-fb59merge.96": 1,
  "0.58.0-vnext.137": 1,
  "0.58.0-vnext.136": 1,
  "0.58.0-vnext.135": 1,
  "0.58.0-vnext-fb59merge.94": 1,
  "0.58.0-vnext.132": 1,
  "0.58.0-vnext.131": 1,
  "0.58.0-vnext.130": 1,
  "0.58.0-vnext.128": 1,
  "0.58.0-vnext.126": 1,
  "0.58.0-vnext.123": 1,
  "0.58.0-vnext.121": 1,
  "0.58.0-vnext.118": 1,
  "0.58.0-vnext.117": 1,
  "0.58.0-vnext.114": 1,
  "0.58.0-vnext.113": 1,
  "0.58.0-vnext.111": 1,
  "0.58.0-vnext.109": 1,
  "0.58.0-vnext.104": 1,
  "0.58.0-vnext.100": 1,
  "0.58.0-vnext.99": 1,
  "0.58.0-vnext.98": 1,
  "0.58.0-vnext.95": 1,
  "0.58.0-vnext.94": 1,
  "0.58.0-vnext.93": 1,
  "0.58.0-vnext.92": 1,
  "0.58.0-vnext-fb59merge.91": 1,
  "0.58.0-vnext.89": 1,
  "0.58.0-vnext.88": 1,
  "0.58.0-vnext.86": 2,
  "0.58.0-vnext.85": 3,
  "0.58.0-vnext.82": 2,
  "0.58.0-vnext.81": 3,
  "0.58.0-vnext.80": 3,
  "0.58.0-vnext.78": 2,
  "0.58.0-vnext.76": 2,
  "0.58.0-vnext.75": 2,
  "0.58.0-vnext.74": 2,
  "0.58.0-vnext.72": 2,
  "0.58.0-rc.0": 2,
  "0.58.0-vnext.68": 2,
  "0.58.0-vnext.67": 2,
  "0.58.0-vnext.66": 3,
  "0.58.0-vnext.64": 2,
  "0.58.0-vnext.61": 2,
  "0.58.0-vnext.57": 2,
  "0.58.0-vnext.54": 2,
  "0.58.0-vnext.53": 2,
  "0.58.0-vnext.52": 2,
  "0.58.0-vnext.50": 2,
  "0.58.0-vnext.49": 2,
  "0.58.0-vnext.48": 2,
  "0.58.0-vnext.47": 2,
  "0.58.0-vnext.46": 2,
  "0.58.0-vnext.45": 1,
  "0.58.0-vnext.44": 2,
  "0.58.0-vnext.43": 1,
  "0.58.0-vnext.41": 1,
  "0.58.0-vnext.39": 1,
  "0.58.0-vnext.37": 1,
  "0.58.0-vnext.34": 2,
  "0.58.0-vnext.31": 1,
  "0.58.0-vnext.26": 1,
  "0.57.1": 65,
  "0.57.0-rc.5": 2,
  "0.57.0-rc.4": 1,
  "0.57.0-rc.3": 1,
  "0.57.0-rc.2": 2,
  "0.57.0-rc.1": 1,
  "0.57.0-rc.0": 9,
  "0.55.0-rc.0": 6,
  "0.53.0": 1,
  "0.52.0": 1,
  "0.54.0-rc.1": 1,
  "0.54.0-rc.0": 1,
  "0.52.0-rc.3": 1,
  "0.52.0-rc.1": 1,
  "0.53.0-rc.1": 1,
  "0.51.0-rc.1": 1,
  "0.50.0": 1,
  "0.51.0-rc.0": 1,
  "0.50.0-rc.2": 1,
  "0.50.0-rc.1": 1,
  "0.49.0-rc.2": 1,
  "0.49.0-rc.0": 1,
  "0.48.0-rc.8": 1,
  "0.48.0-rc.7": 1,
  "0.48.0-rc.6": 1,
  "0.48.0-rc.4": 1,
  "0.48.0-rc.3": 1,
  "0.48.0-rc.1": 1,
  "0.48.0-rc.0": 1,
  "0.47.0-rc.5": 2,
  "0.47.0-rc.4": 1,
  "0.42.1-rc.3": 1,
  "0.46.0-rc.0": 1,
  "0.45.0-rc.0": 2,
  "0.44.0-rc.2": 2,
  "0.44.0-rc.1": 2,
  "0.43.0-rc.1": 2,
  "0.41.0": 3,
  "0.40.0": 2,
  "0.40.0-rc.5": 2,
  "0.41.0-rc.4": 2,
  "0.42.0-rc.4": 2,
  "0.41.0-rc.3": 2,
  "0.42.0-rc.3": 2,
  "0.41.0-rc.1": 155,
  "0.42.0-rc.1": 2,
  "0.41.0-rc.0": 4,
  "0.40.0-rc.0": 2,
  "0.39.1": 7,
  "0.38.0-rc.0": 2,
  "0.36.0": 2,
  "0.36.0-rc.0": 2,
  "0.35.0": 2,
  "0.33.4": 2,
  "0.32.1": 2,
  "0.33.3": 2,
  "0.34.0-rc.0": 2,
  "0.33.0-rc.1": 2,
  "0.33.0-rc.0": 2,
  "0.31.3": 2,
  "0.31.2": 1,
  "1.0.0": 544
}