{
  "37.0.5": 6,
  "45.0.4": 1806,
  "37.0.11": 31,
  "37.0.2": 3,
  "46.0.0-beta.7": 3,
  "37.0.7": 132,
  "37.0.6": 7,
  "28.0.1": 83,
  "47.0.0-alpha.1": 44,
  "39.0.5": 747,
  "42.0.1": 297,
  "37.0.0": 13,
  "32.0.6": 794,
  "0.1.6": 4,
  "31.0.6": 41,
  "42.0.3": 966,
  "45.0.7": 24,
  "46.0.3": 47,
  "45.0.8": 42305,
  "44.0.4": 320,
  "46.0.1": 15,
  "21.0.3": 22,
  "47.0.8": 13456,
  "45.0.6": 4766,
  "32.0.3": 3,
  "16.0.0": 14,
  "25.1.2": 49,
  "46.0.7": 387,
  "35.0.1": 1644,
  "40.0.1": 2506,
  "38.0.8": 85,
  "14.0.2": 4,
  "27.0.1": 27,
  "42.0.4": 472,
  "41.0.1": 2584,
  "43.0.5": 4914,
  "30.0.2": 54,
  "46.0.20": 24010,
  "37.0.4": 9,
  "25.0.0-rc.1": 1,
  "22.1.0": 12,
  "48.0.5": 74167,
  "1.0.0": 4105,
  "38.0.10": 192,
  "29.0.1": 19,
  "32.0.0": 26,
  "18.0.9": 3,
  "21.0.0-rc.3": 2,
  "23.0.3": 2,
  "33.0.2": 4,
  "48.0.0": 936,
  "45.0.1": 115,
  "30.0.1": 33,
  "47.0.12": 6347,
  "39.0.2": 191,
  "18.0.2": 3,
  "46.0.0-beta.2": 4,
  "37.0.10": 18,
  "44.0.2": 28,
  "24.1.1": 10,
  "38.0.0": 10,
  "18.0.4-rc.0": 2,
  "17.0.0": 22,
  "42.0.0": 159,
  "14.0.0": 6,
  "48.0.3": 235,
  "23.0.6": 8,
  "47.0.10": 644,
  "47.0.0-beta.2": 7,
  "31.0.1": 3,
  "34.0.4": 295,
  "15.1.3": 13,
  "47.0.0": 1398,
  "47.0.11": 1411,
  "45.0.0-beta.9": 24,
  "21.0.2": 6,
  "46.0.10": 5382,
  "46.0.9": 2350,
  "46.0.14": 824,
  "47.0.5": 103,
  "22.0.3": 2,
  "29.0.0": 10,
  "45.0.3": 170,
  "34.0.1": 48,
  "47.0.4": 19,
  "47.0.13": 107600,
  "27.1.0": 12,
  "46.0.6": 110,
  "27.1.1": 58,
  "15.0.0": 3,
  "46.0.16": 10983,
  "38.0.9": 126,
  "34.0.3": 41,
  "47.0.0-beta.5": 5,
  "47.0.0-beta.7": 13,
  "23.0.4": 3,
  "37.0.8": 561,
  "40.0.0": 529,
  "46.0.8": 460,
  "44.0.5": 606,
  "46.0.11": 8,
  "32.0.0-rc.0": 2,
  "42.0.0-alpha.1": 3,
  "31.0.2": 6,
  "27.0.2": 12,
  "33.0.0-rc.5": 3,
  "32.0.4": 3,
  "32.0.0-rc.1": 2,
  "46.0.12": 6,
  "18.0.3": 7,
  "45.0.0-beta.2": 3,
  "15.1.2": 3,
  "29.0.0-rc.0": 3,
  "35.0.0-rc.0": 3,
  "23.1.0": 2,
  "26.0.0-rc.0": 3,
  "45.0.0-beta.6": 3,
  "48.0.0-beta.1": 4,
  "33.0.0-alpha.web.3": 2,
  "46.0.18": 30,
  "34.0.0-experiment.1": 2,
  "47.0.0-beta.3": 2,
  "43.0.0-alpha.1": 3,
  "48.0.4": 55850,
  "46.0.0": 1178,
  "38.0.3": 7,
  "27.0.2-rc.0": 3,
  "26.0.0": 15,
  "32.0.0-rc.4": 2,
  "29.0.0-rc.3": 3,
  "42.0.0-beta.0": 2,
  "34.0.0-experiment.3": 3,
  "31.0.0-rc.3": 5,
  "43.0.0-alpha.2": 2,
  "46.0.0-beta.6": 14,
  "0.1.3": 1,
  "30.0.0-rc.0": 2,
  "45.0.0-beta.1": 4,
  "27.0.0-rc.0": 2,
  "34.0.0-experiment.0": 3,
  "44.0.1": 74,
  "43.0.4": 1766,
  "36.0.2": 835,
  "45.0.0-beta.3": 3,
  "48.0.2": 11,
  "41.0.0-beta.2": 16,
  "43.0.1": 359,
  "47.0.6": 2235,
  "48.0.0-beta.2": 85,
  "37.0.3": 28,
  "37.0.12": 650,
  "47.0.7": 4184,
  "47.0.3": 1945,
  "45.0.5": 2131,
  "41.0.0": 108,
  "45.0.0": 1790,
  "38.0.11": 494,
  "47.0.0-beta.4": 2,
  "47.0.0-beta.8": 19,
  "30.0.0": 5,
  "45.0.0-beta.5": 2,
  "40.0.0-beta.2": 2,
  "33.0.1": 3,
  "20.1.4": 8,
  "31.0.5": 8,
  "31.0.0": 6,
  "27.0.1-rc.0": 2,
  "48.0.0-beta.0": 3,
  "45.0.2": 689,
  "44.0.0-beta.2": 9,
  "23.0.1": 2,
  "38.0.2": 5,
  "33.0.7": 87,
  "39.0.3": 148,
  "46.0.15": 2406,
  "25.0.0": 23,
  "42.0.0-beta.1": 2,
  "46.0.0-beta.3": 2,
  "21.0.0-rc.4": 1,
  "23.0.0-rc.0": 1,
  "33.0.0-alpha.web.1": 3,
  "20.1.2": 1,
  "36.0.1": 3,
  "29.0.1-rc.0": 2,
  "41.0.0-alpha.0": 3,
  "27.0.2-rc.1": 2,
  "24.0.3": 3,
  "34.0.0-experiment.6": 2,
  "40.0.0-alpha.0": 4,
  "33.0.0-alpha.0": 2,
  "41.0.0-beta.0": 2,
  "29.0.0-rc.2": 3,
  "41.0.0-beta.3": 4,
  "32.0.0-rc.2": 2,
  "21.0.0-alpha.2": 2,
  "22.0.2": 1,
  "38.0.7-rc.0": 2,
  "43.0.0-beta.1": 3,
  "21.0.0-rc.0": 1,
  "41.0.0-beta.1": 2,
  "36.0.0-rc.0": 2,
  "44.0.0-alpha.0": 3,
  "18.0.0-rc.3": 1,
  "46.0.4": 5,
  "40.0.0-beta.0": 3,
  "23.0.2": 2,
  "23.0.0": 2,
  "36.0.0": 65,
  "17.0.0-rc.4": 2,
  "33.0.0-rc.6": 2,
  "34.0.2": 4,
  "37.0.9": 6,
  "32.0.2": 5,
  "44.0.0-beta.0": 2,
  "24.0.0-rc.1": 1,
  "22.0.4": 3,
  "40.0.0-beta.4": 4,
  "34.0.0-experiment.4": 2,
  "32.0.2-rc.0": 2,
  "25.0.1": 3,
  "42.0.0-beta.2": 3,
  "42.0.0-alpha.0": 2,
  "40.0.0-beta.1": 3,
  "26.1.1": 11,
  "28.0.0-rc.1": 3,
  "31.0.3": 3,
  "25.1.0": 3,
  "33.0.0-alpha.web.0": 2,
  "47.0.2": 4,
  "48.0.1": 1297,
  "47.0.1": 81,
  "18.0.0": 2,
  "38.0.4": 12,
  "19.0.0": 2,
  "46.0.0-alpha.0": 2,
  "46.0.5": 5,
  "44.0.6": 17647,
  "42.0.5": 1709,
  "46.0.19": 6516,
  "46.0.2": 440,
  "43.0.0": 483,
  "44.0.0": 443,
  "46.0.13": 2511,
  "47.0.9": 7321,
  "38.0.5": 4,
  "34.0.0-rc.2": 2,
  "38.0.1": 6,
  "34.0.0-experiment.2": 3,
  "41.0.0-alpha.1": 3,
  "43.0.0-alpha.0": 4,
  "33.0.0-alpha.1": 2,
  "34.0.0-experiment.8": 3,
  "33.0.0": 490,
  "35.0.0": 98,
  "43.0.2": 153,
  "31.0.0-rc.0": 3,
  "33.0.0-rc.1": 3,
  "43.0.3": 1087,
  "46.0.0-alpha.3": 5,
  "33.0.5": 15,
  "15.0.1": 5,
  "46.0.17": 5488,
  "39.0.4": 195,
  "44.0.3": 288,
  "33.0.6": 6,
  "25.0.0-rc.0": 1,
  "20.0.0-alpha.5": 1,
  "18.0.6": 1,
  "43.0.0-beta.2": 3,
  "46.0.0-beta.1": 3,
  "25.1.1": 3,
  "22.0.0-rc.0": 1,
  "34.0.0-rc.3": 3,
  "32.0.5": 5,
  "46.0.0-alpha.1": 3,
  "33.0.0-rc.3": 2,
  "46.0.0-alpha.2": 2,
  "40.0.0-beta.5": 3,
  "34.0.0-experiment.7": 2,
  "33.0.4": 3,
  "45.0.0-beta.4": 3,
  "22.0.0": 2,
  "42.0.2": 5,
  "20.0.0-alpha.6": 1,
  "18.0.0-alpha.0": 1,
  "0.1.1": 1,
  "32.0.1": 10,
  "33.0.3": 3,
  "45.0.0-beta.7": 3,
  "33.0.0-rc.7": 3,
  "26.0.0-rc.1": 3,
  "46.0.0-beta.4": 2,
  "34.0.0-rc.0": 3,
  "45.0.0-beta.8": 3,
  "20.1.1": 1,
  "47.0.0-beta.1": 7,
  "39.0.0": 18,
  "28.0.0-rc.2": 3,
  "43.0.0-beta.3": 4,
  "43.0.0-beta.4": 7,
  "46.0.0-beta.5": 3,
  "33.0.0-rc.4": 3,
  "0.1.7": 2,
  "21.0.0-alpha.1": 1,
  "15.0.2": 1,
  "44.0.0-beta.1": 3,
  "26.1.0": 5,
  "23.1.1": 24,
  "28.0.0-rc.0": 3,
  "43.0.0-beta.0": 3,
  "33.0.0-rc.2": 2,
  "24.1.0": 3,
  "41.0.0-beta.4": 3,
  "31.0.0-rc.1": 3,
  "33.0.0-alpha.web.2": 3,
  "21.0.0": 1,
  "47.0.0-beta.6": 2,
  "22.0.1": 2,
  "19.0.1": 4,
  "19.0.0-rc.0": 1,
  "30.0.0-rc.1": 4,
  "31.0.0-rc.2": 3,
  "15.0.0-rc.1": 1,
  "19.0.0-alpha.0": 1,
  "38.0.6": 5,
  "15.0.1-beta.1": 1,
  "17.0.0-rc.2": 1,
  "21.0.0-rc.1": 1,
  "19.0.0-rc.2": 1,
  "20.0.0-alpha.2": 1,
  "20.0.0-alpha.0": 1,
  "17.0.0-rc.3": 1,
  "43.0.0-alpha.3": 2,
  "34.0.0-experiment.5": 2,
  "31.0.4": 4,
  "39.0.1": 5,
  "28.0.0": 8,
  "40.0.0-beta.3": 3,
  "26.0.0-rc.2": 3,
  "20.1.3": 2,
  "33.0.0-rc.0": 3,
  "32.0.0-rc.3": 3,
  "20.0.0-alpha.4": 1,
  "19.0.0-rc.5": 1,
  "38.0.7": 5,
  "27.0.0": 9,
  "16.0.0-rc.1": 1,
  "34.0.0-rc.1": 2,
  "16.0.0-beta.0": 1,
  "37.0.1": 4,
  "22.0.0-rc.1": 1,
  "19.0.0-rc.4": 1,
  "23.0.0-rc.1": 2,
  "19.0.0-rc.6": 2,
  "24.0.1": 1,
  "0.1.4": 1,
  "20.0.0-alpha.7": 1,
  "0.1.5": 2,
  "17.0.0-rc.1": 1,
  "20.0.4": 1
}