{
  "47.0.13": 15802,
  "47.0.0-beta.8": 5,
  "34.0.1": 28,
  "42.0.2": 6,
  "27.1.0": 17,
  "47.0.4": 17,
  "45.0.3": 34,
  "46.0.6": 44,
  "42.0.0-alpha.0": 2,
  "48.0.0-beta.2": 17,
  "19.0.0-rc.5": 3,
  "43.0.1": 156,
  "33.0.4": 25,
  "49.0.12": 2370,
  "46.0.0-alpha.2": 2,
  "20.0.3": 4,
  "46.0.0-alpha.1": 2,
  "29.0.0-rc.0": 2,
  "35.0.1": 1558,
  "49.0.0-alpha.4": 13,
  "48.0.16": 2957,
  "42.0.0-beta.1": 2,
  "48.0.7": 921,
  "25.1.2": 30,
  "35.0.0-rc.0": 3,
  "15.1.2": 4,
  "49.0.0-beta.2": 2,
  "49.0.0": 3108,
  "33.0.7": 60,
  "31.0.3": 9,
  "46.0.15": 271,
  "39.0.3": 70,
  "48.0.21": 61411,
  "19.0.0-rc.1": 3,
  "25.0.0": 23,
  "48.0.11": 3321,
  "49.0.3": 9450,
  "49.0.2": 606,
  "43.0.0-alpha.2": 2,
  "49.0.0-alpha.8": 2,
  "28.0.1": 27,
  "18.0.6": 3,
  "37.0.6": 24,
  "0.1.7": 7,
  "49.0.14": 5575,
  "37.0.0": 14,
  "29.0.1-rc.0": 2,
  "36.0.1": 13,
  "20.1.2": 4,
  "27.0.2": 18,
  "32.0.6": 97,
  "48.0.6": 1370,
  "49.0.6": 17002,
  "23.0.0-rc.0": 3,
  "32.0.4": 18,
  "31.0.6": 33,
  "46.0.12": 21,
  "47.0.0-alpha.1": 14,
  "0.1.6": 5,
  "32.0.0-rc.1": 2,
  "39.0.5": 435,
  "49.0.0-beta.5": 5,
  "23.0.5": 5,
  "31.0.0": 6,
  "27.1.1": 61,
  "48.0.13": 150,
  "33.0.1": 17,
  "23.0.0-rc.2": 4,
  "31.0.5": 22,
  "49.0.4": 1793,
  "25.0.1": 6,
  "34.0.0-experiment.4": 3,
  "48.0.0-beta.0": 5,
  "45.0.0-beta.4": 2,
  "49.0.13": 49341,
  "48.0.8": 182,
  "47.0.12": 495,
  "23.0.3": 8,
  "30.0.1": 13,
  "48.0.0": 1934,
  "46.0.18": 16,
  "33.0.2": 8,
  "33.0.0-alpha.web.3": 2,
  "34.0.0-experiment.1": 2,
  "45.0.1": 36,
  "47.0.5": 130,
  "46.0.14": 82,
  "47.0.11": 85,
  "47.0.0": 415,
  "21.0.2": 8,
  "46.0.9": 514,
  "34.0.4": 205,
  "30.0.0": 6,
  "29.0.0": 12,
  "15.1.3": 7,
  "43.0.0-beta.2": 2,
  "40.0.0-beta.2": 3,
  "22.0.3": 5,
  "45.0.5": 491,
  "49.0.10": 9615,
  "49.0.1": 43,
  "47.0.3": 289,
  "22.0.0-rc.0": 3,
  "47.0.7": 70,
  "36.0.0": 177,
  "37.0.12": 703,
  "46.0.0-beta.1": 2,
  "18.0.0-rc.2": 3,
  "34.0.2": 5,
  "34.0.0-rc.3": 2,
  "25.1.1": 4,
  "17.0.0-rc.4": 3,
  "50.0.0-alpha.0": 5,
  "49.0.8": 14737,
  "40.0.0": 158,
  "44.0.5": 190,
  "34.0.3": 38,
  "38.0.9": 67,
  "45.0.2": 35,
  "44.0.0-beta.2": 13,
  "38.0.2": 5,
  "23.0.4": 13,
  "46.0.8": 81,
  "37.0.8": 873,
  "18.0.4": 3,
  "46.0.16": 827,
  "20.0.0-alpha.2": 3,
  "20.0.2": 4,
  "47.0.0-beta.6": 5,
  "47.0.0-beta.7": 5,
  "31.0.2": 19,
  "45.0.4": 157,
  "48.0.9": 5430,
  "49.0.5": 1740,
  "37.0.11": 25,
  "20.1.0": 3,
  "50.0.0-alpha.5": 11,
  "37.0.5": 5,
  "34.0.0-experiment.6": 3,
  "37.0.7": 145,
  "46.0.11": 9,
  "0.1.2": 6,
  "48.0.0-beta.1": 5,
  "14.0.2": 6,
  "38.0.8": 70,
  "40.0.1": 895,
  "27.0.1": 21,
  "41.0.0-alpha.0": 3,
  "24.0.3": 4,
  "50.0.0-alpha.1": 6,
  "27.0.2-rc.1": 2,
  "46.0.0": 778,
  "23.0.2": 3,
  "46.0.4": 31,
  "44.0.4": 88,
  "46.0.3": 15,
  "27.0.2-rc.0": 2,
  "16.0.0": 11,
  "20.0.0-alpha.5": 3,
  "47.0.8": 1829,
  "48.0.15": 3474,
  "46.0.1": 18,
  "38.0.3": 19,
  "42.0.3": 524,
  "21.0.3": 23,
  "15.0.2": 15,
  "48.0.4": 1658,
  "45.0.6": 1030,
  "45.0.7": 27,
  "48.0.19": 21009,
  "41.0.0": 52,
  "37.0.9": 8,
  "38.0.11": 201,
  "45.0.0": 451,
  "24.0.0": 5,
  "49.0.11": 17608,
  "21.0.0-rc.0": 3,
  "22.1.0": 9,
  "22.0.2": 5,
  "21.0.0-rc.1": 4,
  "25.0.0-rc.1": 4,
  "41.0.1": 1065,
  "50.0.0-alpha.2": 100,
  "19.0.0-rc.3": 3,
  "43.0.5": 1681,
  "30.0.2": 29,
  "17.0.0-rc.2": 3,
  "46.0.20": 1062,
  "47.0.14": 23598,
  "37.0.4": 25,
  "42.0.4": 353,
  "48.0.12": 616,
  "49.0.0-beta.4": 18,
  "38.0.10": 111,
  "1.0.0": 26,
  "50.0.0-alpha.3": 6,
  "21.0.0-rc.3": 3,
  "48.0.10": 2035,
  "48.0.5": 1153,
  "49.0.0-alpha.3": 8,
  "48.0.20": 32383,
  "29.0.0-rc.2": 3,
  "30.0.0-rc.0": 2,
  "25.0.0-rc.0": 4,
  "47.0.10": 85,
  "42.0.0": 157,
  "48.0.18": 1578,
  "50.0.0-alpha.6": 332,
  "23.0.6": 12,
  "29.0.0-rc.3": 2,
  "31.0.1": 3,
  "48.0.3": 44,
  "18.0.1": 3,
  "34.0.0-experiment.3": 3,
  "17.0.0": 29,
  "34.0.0-rc.2": 2,
  "21.0.0-alpha.0": 3,
  "45.0.0-beta.3": 3,
  "48.0.14": 20,
  "49.0.0-alpha.5": 2,
  "18.0.4-rc.0": 4,
  "36.0.2": 773,
  "38.0.1": 25,
  "18.0.0-rc.1": 3,
  "20.0.1": 3,
  "38.0.0": 10,
  "33.0.0-alpha.1": 2,
  "44.0.1": 63,
  "38.0.5": 9,
  "43.0.4": 122,
  "18.0.2": 3,
  "33.0.6": 18,
  "44.0.2": 18,
  "19.0.1": 7,
  "37.0.10": 18,
  "41.0.0-beta.2": 3,
  "19.0.0-rc.7": 3,
  "19.0.0-rc.0": 3,
  "21.0.0-rc.5": 3,
  "48.0.2": 12,
  "39.0.2": 14,
  "32.0.5": 2,
  "47.0.6": 252,
  "49.0.0-alpha.9": 2,
  "20.0.0-alpha.4": 3,
  "15.0.1-beta.1": 10,
  "20.0.0": 3,
  "33.0.0-rc.3": 2,
  "40.0.0-beta.5": 2,
  "38.0.6": 23,
  "33.0.0-rc.5": 2,
  "42.0.1": 60,
  "46.0.0-beta.3": 2,
  "33.0.0-alpha.web.1": 3,
  "21.0.0-rc.4": 3,
  "22.0.0": 5,
  "15.0.0": 3,
  "17.0.0-rc.3": 3,
  "20.0.0-alpha.1": 3,
  "32.0.2-rc.0": 2,
  "42.0.0-beta.2": 3,
  "20.1.4": 9,
  "27.0.1-rc.0": 2,
  "45.0.0-beta.9": 2,
  "45.0.0-beta.5": 2,
  "40.0.0-beta.4": 2,
  "49.0.0-alpha.10": 2,
  "49.0.0-beta.3": 2,
  "46.0.10": 1234,
  "31.0.0-rc.2": 2,
  "33.0.0-rc.6": 2,
  "41.0.0-beta.1": 2,
  "45.0.8": 9252,
  "36.0.0-rc.0": 2,
  "44.0.0-alpha.0": 2,
  "18.0.0-rc.3": 3,
  "40.0.0-beta.0": 2,
  "32.0.3": 11,
  "19.0.0-alpha.0": 3,
  "20.0.5": 3,
  "21.0.0": 5,
  "24.0.0-rc.1": 3,
  "47.0.0-beta.5": 2,
  "23.0.1": 3,
  "22.0.4": 4,
  "22.0.1": 4,
  "49.0.0-beta.0": 2,
  "46.0.0-alpha.0": 2,
  "40.0.0-alpha.0": 3,
  "42.0.0-alpha.1": 2,
  "19.0.0-rc.2": 3,
  "37.0.2": 11,
  "46.0.0-beta.7": 3,
  "20.1.1": 3,
  "32.0.0-rc.0": 2,
  "47.0.2": 11,
  "0.1.1": 5,
  "26.0.0-rc.0": 3,
  "47.0.0-beta.4": 2,
  "40.0.0-beta.1": 2,
  "48.0.17": 4592,
  "46.0.5": 24,
  "24.0.1": 5,
  "44.0.6": 14165,
  "44.0.0": 482,
  "46.0.2": 109,
  "26.1.0": 3,
  "46.0.21": 4226,
  "46.0.13": 511,
  "47.0.9": 582,
  "46.0.19": 263,
  "40.0.0-beta.3": 2,
  "49.0.16": 121551,
  "37.0.1": 24,
  "14.0.1": 11,
  "32.0.0-rc.3": 2,
  "42.0.5": 1181,
  "44.0.0-beta.1": 2,
  "26.0.0-rc.2": 3,
  "34.0.0-rc.0": 2,
  "38.0.7": 3,
  "43.0.0-alpha.3": 2,
  "49.0.0-alpha.7": 2,
  "19.0.0-rc.4": 3,
  "46.0.0-beta.4": 2,
  "48.0.1": 541,
  "33.0.3": 27,
  "18.0.0": 3,
  "38.0.4": 6,
  "19.0.0": 3,
  "49.0.15": 4190,
  "32.0.1": 12,
  "47.0.1": 18,
  "26.0.0-rc.1": 3,
  "45.0.0-beta.8": 3,
  "26.1.1": 7,
  "28.0.0-rc.1": 2,
  "25.1.0": 4,
  "22.0.0-rc.1": 3,
  "33.0.5": 5,
  "34.0.0-experiment.8": 3,
  "15.0.1": 4,
  "34.0.0-experiment.5": 2,
  "24.0.0-rc.0": 3,
  "41.0.0-beta.4": 2,
  "33.0.0": 19,
  "43.0.2": 38,
  "31.0.4": 19,
  "31.0.0-rc.0": 3,
  "20.0.0-alpha.7": 3,
  "49.0.9": 10304,
  "23.1.1": 9,
  "43.0.3": 474,
  "24.1.0": 5,
  "49.0.7": 9419,
  "35.0.0": 76,
  "18.0.3": 4,
  "46.0.7": 94,
  "45.0.0-beta.2": 2,
  "49.0.0-alpha.6": 2,
  "31.0.0-rc.3": 2,
  "21.0.0-alpha.1": 3,
  "49.0.0-alpha.2": 2,
  "23.0.0-rc.1": 4,
  "39.0.1": 5,
  "17.0.0-rc.1": 3,
  "33.0.0-rc.4": 2,
  "39.0.4": 151,
  "46.0.17": 582,
  "39.0.0": 14,
  "28.0.0": 6,
  "20.0.4": 4,
  "46.0.0-beta.5": 2,
  "44.0.3": 36,
  "19.0.0-rc.6": 3,
  "43.0.0-beta.4": 2,
  "16.0.0-rc.1": 3,
  "43.0.0-alpha.1": 2,
  "20.0.0-alpha.3": 3,
  "47.0.0-beta.3": 9,
  "20.0.0-alpha.6": 3,
  "44.0.0-beta.0": 2,
  "32.0.2": 3,
  "18.0.0-alpha.0": 3,
  "41.0.0-beta.0": 2,
  "20.0.0-alpha.0": 3,
  "26.0.0": 6,
  "32.0.0-rc.4": 2,
  "14.0.0": 3,
  "42.0.0-beta.0": 2,
  "43.0.0-beta.1": 2,
  "21.0.0-alpha.2": 3,
  "38.0.7-rc.0": 2,
  "41.0.0-alpha.1": 2,
  "34.0.0-experiment.2": 2,
  "24.1.1": 10,
  "23.0.0": 4,
  "24.0.2": 3,
  "46.0.0-beta.2": 2,
  "49.0.0-alpha.1": 2,
  "29.0.1": 12,
  "34.0.0-experiment.0": 2,
  "30.0.0-rc.1": 2,
  "45.0.0-beta.1": 3,
  "32.0.0": 22,
  "0.1.3": 4,
  "32.0.0-rc.2": 2,
  "18.0.9": 9,
  "46.0.0-beta.6": 3,
  "18.0.5": 3,
  "27.0.0-rc.0": 2,
  "37.0.3": 13,
  "34.0.0-experiment.7": 3,
  "15.0.0-rc.1": 4,
  "33.0.0-rc.0": 2,
  "20.1.3": 3,
  "43.0.0": 173,
  "0.1.4": 5,
  "16.0.0-beta.0": 3,
  "23.1.0": 4,
  "18.0.8": 4,
  "34.0.0-rc.1": 2,
  "47.0.0-beta.1": 2,
  "15.0.1-beta.0": 3,
  "33.0.0-alpha.web.0": 3,
  "45.0.0-beta.6": 2,
  "45.0.0-beta.7": 2,
  "33.0.0-rc.7": 2,
  "33.0.0-alpha.0": 2,
  "47.0.0-beta.2": 2,
  "21.0.1": 4,
  "41.0.0-beta.3": 2,
  "0.1.5": 4,
  "18.0.0-alpha.1": 3,
  "50.0.0-alpha.4": 177,
  "33.0.0-rc.1": 3,
  "43.0.0-beta.0": 2,
  "28.0.0-rc.0": 2,
  "27.0.0": 2,
  "46.0.0-alpha.3": 2,
  "49.0.0-beta.1": 1,
  "33.0.0-rc.2": 2,
  "31.0.0-rc.1": 2,
  "33.0.0-alpha.web.2": 2,
  "43.0.0-alpha.0": 2,
  "43.0.0-beta.3": 2,
  "28.0.0-rc.2": 2
}