{
  "25.0.0": 93,
  "19.0.0-rc.1": 5,
  "20.0.3": 6,
  "40.0.0-beta.5": 5,
  "48.0.7": 11186,
  "23.1.0": 6,
  "18.0.3": 27,
  "28.0.1": 137,
  "18.0.6": 9,
  "37.0.9": 14,
  "24.0.0": 5,
  "32.0.2": 21,
  "41.0.0": 379,
  "18.0.0-alpha.0": 5,
  "20.0.0-alpha.6": 5,
  "44.0.0-beta.0": 1,
  "37.0.6": 29,
  "18.0.0-rc.2": 6,
  "29.0.1": 39,
  "46.0.0-beta.6": 62,
  "42.0.0-beta.1": 1,
  "32.0.2-rc.0": 5,
  "25.0.1": 6,
  "45.0.1": 44,
  "20.0.0-alpha.3": 5,
  "0.1.7": 5,
  "43.0.0-alpha.2": 1,
  "48.0.2": 7,
  "41.0.0-beta.0": 36,
  "20.0.0-alpha.0": 5,
  "47.0.12": 4301,
  "48.0.0": 998,
  "33.0.0-alpha.web.3": 7,
  "42.0.1": 1166,
  "27.0.2": 40,
  "36.0.1": 54,
  "39.0.5": 7431,
  "46.0.12": 1,
  "33.0.0-alpha.web.1": 13,
  "32.0.0-rc.1": 6,
  "20.1.2": 6,
  "29.0.1-rc.0": 5,
  "21.0.0-rc.4": 5,
  "43.0.0-beta.2": 1,
  "40.0.0-beta.4": 5,
  "45.0.0-beta.9": 2,
  "47.0.0-alpha.1": 45,
  "0.1.6": 5,
  "38.0.6": 6,
  "15.0.1-beta.1": 5,
  "34.0.0-experiment.7": 6,
  "38.0.0": 58,
  "18.0.0-rc.1": 5,
  "18.0.4-rc.0": 6,
  "25.1.2": 124,
  "37.0.0": 60,
  "23.0.0-rc.0": 5,
  "37.0.12": 4022,
  "45.0.5": 1274,
  "47.0.7": 1506,
  "36.0.0": 244,
  "34.0.0-rc.3": 5,
  "22.0.3": 10,
  "46.0.10": 3075,
  "30.0.0": 8,
  "29.0.0": 20,
  "34.0.1": 208,
  "27.1.1": 147,
  "23.0.5": 7,
  "27.0.1-rc.0": 5,
  "33.0.1": 7,
  "48.0.0-beta.0": 9,
  "45.0.2": 522,
  "22.0.4": 11,
  "46.0.16": 6415,
  "23.0.4": 10,
  "20.0.2": 7,
  "20.0.5": 5,
  "47.0.1": 130,
  "38.0.7": 8,
  "27.0.1": 172,
  "37.0.8": 671,
  "21.0.0": 13,
  "22.0.1": 7,
  "47.0.0-beta.7": 6,
  "47.0.0-beta.6": 6,
  "46.0.20": 19619,
  "17.0.0-rc.2": 5,
  "38.0.7-rc.0": 5,
  "46.0.4": 1,
  "36.0.0-rc.0": 7,
  "18.0.0-rc.3": 5,
  "23.0.2": 5,
  "46.0.0": 760,
  "44.0.0-alpha.0": 1,
  "47.0.9": 3964,
  "24.0.1": 6,
  "32.0.0-rc.3": 5,
  "0.1.4": 6,
  "46.0.5": 2,
  "33.0.0": 518,
  "28.0.0-rc.0": 5,
  "33.0.0-rc.2": 6,
  "33.0.0-rc.1": 6,
  "18.0.0-alpha.1": 5,
  "43.0.0-beta.0": 1,
  "46.0.17": 4461,
  "20.0.4": 5,
  "18.0.8": 5,
  "47.0.0-beta.1": 1,
  "33.0.0-rc.4": 6,
  "38.0.10": 2150,
  "0.1.3": 5,
  "30.0.0-rc.1": 5,
  "48.0.10": 7889,
  "46.0.6": 140,
  "42.0.0-alpha.0": 1,
  "37.0.7": 542,
  "48.0.9": 117685,
  "19.0.0-rc.2": 5,
  "40.0.0-alpha.0": 7,
  "15.0.1-beta.0": 5,
  "42.0.0-alpha.1": 1,
  "19.0.0": 8,
  "37.0.10": 152,
  "44.0.2": 166,
  "33.0.6": 27,
  "41.0.0-beta.2": 5,
  "19.0.0-rc.7": 5,
  "48.0.3": 244,
  "21.0.1": 5,
  "14.0.0": 8,
  "42.0.0-beta.0": 1,
  "38.0.5": 7,
  "20.0.1": 5,
  "46.0.13": 1007,
  "37.0.1": 10,
  "41.0.0-beta.4": 1,
  "44.0.3": 2343,
  "28.0.0": 40,
  "19.0.0-rc.6": 5,
  "34.0.0-rc.1": 5,
  "1.0.0": 5433,
  "48.0.5": 4723,
  "32.0.0": 130,
  "27.0.0-rc.0": 5,
  "34.0.0-experiment.0": 5,
  "18.0.5": 5,
  "22.0.0-rc.0": 6,
  "25.1.1": 5,
  "17.0.0-rc.4": 5,
  "31.0.6": 217,
  "32.0.4": 23,
  "33.0.0-rc.5": 5,
  "15.1.2": 16,
  "31.0.0-rc.3": 5,
  "21.0.0-alpha.1": 5,
  "30.0.1": 61,
  "48.0.8": 1693,
  "46.0.18": 23,
  "23.0.3": 7,
  "33.0.2": 6,
  "24.0.2": 12,
  "19.0.0-rc.0": 5,
  "42.0.4": 2430,
  "21.0.0-rc.0": 5,
  "43.0.0-beta.1": 1,
  "18.0.9": 21,
  "25.0.0-rc.0": 5,
  "30.0.0-rc.0": 6,
  "0.1.1": 7,
  "47.0.2": 6,
  "26.0.0-rc.0": 5,
  "26.0.0": 43,
  "18.0.1": 5,
  "37.0.3": 205,
  "47.0.6": 1512,
  "33.0.0-rc.3": 5,
  "31.0.1": 5,
  "34.0.0-experiment.3": 5,
  "18.0.4": 8,
  "20.0.0-alpha.2": 5,
  "39.0.3": 3685,
  "46.0.15": 1344,
  "26.1.1": 51,
  "31.0.3": 8,
  "22.0.0-rc.1": 6,
  "25.1.0": 5,
  "28.0.0-rc.1": 5,
  "38.0.11": 2186,
  "45.0.0": 947,
  "43.0.4": 4499,
  "33.0.0-alpha.1": 5,
  "21.0.0-alpha.0": 6,
  "35.0.1": 2422,
  "46.0.7": 188,
  "29.0.0-rc.0": 6,
  "35.0.0-rc.0": 5,
  "46.0.3": 34,
  "16.0.0": 25,
  "45.0.8": 19587,
  "20.0.0-alpha.5": 5,
  "27.0.2-rc.0": 5,
  "15.0.2": 6,
  "39.0.2": 685,
  "19.0.1": 24,
  "47.0.11": 1134,
  "40.0.0-beta.2": 26,
  "24.1.1": 20,
  "17.0.0": 45,
  "41.0.0-alpha.1": 21,
  "34.0.0-experiment.2": 5,
  "34.0.0-rc.2": 5,
  "45.0.4": 923,
  "37.0.11": 369,
  "20.1.0": 5,
  "46.0.9": 1448,
  "47.0.5": 102,
  "46.0.14": 444,
  "47.0.0-beta.8": 34,
  "40.0.0-beta.1": 5,
  "47.0.3": 1314,
  "34.0.2": 9,
  "14.0.2": 7,
  "33.0.0-alpha.web.0": 5,
  "36.0.2": 3220,
  "38.0.1": 21,
  "44.0.1": 4939,
  "43.0.0-alpha.0": 1,
  "47.0.13": 77799,
  "37.0.5": 54,
  "37.0.2": 5,
  "31.0.2": 22,
  "32.0.6": 3068,
  "48.0.6": 10064,
  "48.0.0-beta.2": 23,
  "43.0.1": 2368,
  "20.0.0": 5,
  "20.0.0-alpha.4": 5,
  "27.1.0": 44,
  "47.0.4": 141,
  "42.0.2": 4,
  "45.0.3": 210,
  "44.0.0": 2498,
  "43.0.0": 1634,
  "46.0.19": 3433,
  "46.0.2": 332,
  "38.0.8": 1567,
  "40.0.1": 36420,
  "41.0.0-alpha.0": 15,
  "27.0.2-rc.1": 5,
  "24.0.3": 6,
  "42.0.0": 840,
  "47.0.10": 309,
  "23.0.6": 59,
  "33.0.0-alpha.0": 7,
  "32.0.0-rc.4": 5,
  "29.0.0-rc.3": 6,
  "22.0.0": 8,
  "17.0.0-rc.3": 6,
  "20.0.0-alpha.1": 6,
  "15.0.0": 5,
  "42.0.0-beta.2": 1,
  "34.0.0-experiment.1": 5,
  "43.0.0-alpha.1": 1,
  "23.0.0-rc.2": 6,
  "31.0.0": 5,
  "34.0.0-experiment.4": 5,
  "43.0.5": 13441,
  "22.1.0": 28,
  "41.0.1": 8569,
  "22.0.2": 7,
  "21.0.0-rc.1": 5,
  "25.0.0-rc.1": 5,
  "21.0.0-alpha.2": 5,
  "31.0.5": 27,
  "20.1.4": 39,
  "43.0.0-beta.4": 17,
  "43.0.0-beta.3": 35,
  "28.0.0-rc.2": 7,
  "34.0.0-experiment.6": 5,
  "20.1.1": 8,
  "46.0.11": 1,
  "39.0.1": 7,
  "23.0.0-rc.1": 5,
  "16.0.0-rc.1": 5,
  "17.0.0-rc.1": 5,
  "44.0.4": 3262,
  "41.0.0-beta.1": 113,
  "21.0.3": 79,
  "32.0.3": 16,
  "45.0.6": 3134,
  "45.0.7": 25,
  "47.0.8": 8864,
  "19.0.0-alpha.0": 5,
  "40.0.0-beta.0": 5,
  "23.0.0": 10,
  "21.0.0-rc.5": 5,
  "18.0.2": 5,
  "38.0.9": 2992,
  "46.0.8": 299,
  "38.0.2": 10,
  "40.0.0": 7510,
  "44.0.5": 10648,
  "34.0.3": 110,
  "44.0.0-beta.2": 10,
  "24.0.0-rc.1": 5,
  "23.0.1": 5,
  "32.0.0-rc.2": 5,
  "29.0.0-rc.2": 5,
  "41.0.0-beta.3": 1,
  "21.0.0-rc.3": 6,
  "15.0.1": 7,
  "33.0.5": 32,
  "31.0.0-rc.1": 6,
  "34.0.0-experiment.8": 6,
  "39.0.4": 2005,
  "39.0.0": 247,
  "43.0.2": 1557,
  "35.0.0": 498,
  "31.0.0-rc.0": 6,
  "31.0.4": 22,
  "24.0.0-rc.0": 6,
  "33.0.0-alpha.web.2": 5,
  "24.1.0": 5,
  "20.0.0-alpha.7": 6,
  "0.1.5": 6,
  "33.0.4": 14,
  "32.0.5": 11,
  "19.0.0-rc.5": 5,
  "43.0.3": 6443,
  "23.1.1": 45,
  "27.0.0": 13,
  "34.0.0-experiment.5": 5,
  "20.1.3": 7,
  "44.0.0-beta.1": 5,
  "16.0.0-beta.0": 6,
  "33.0.0-rc.0": 5,
  "26.1.0": 6,
  "40.0.0-beta.3": 5,
  "14.0.1": 5,
  "26.0.0-rc.2": 6,
  "26.0.0-rc.1": 5,
  "19.0.0-rc.4": 5,
  "34.0.0-rc.0": 6,
  "43.0.0-alpha.3": 1,
  "33.0.7": 6951,
  "33.0.3": 336,
  "38.0.4": 49,
  "32.0.1": 51,
  "48.0.1": 748,
  "33.0.0-rc.7": 5,
  "18.0.0": 5,
  "21.0.2": 17,
  "15.1.3": 15,
  "34.0.4": 773,
  "47.0.0": 744,
  "42.0.5": 7465,
  "44.0.6": 106183,
  "37.0.4": 25,
  "30.0.2": 144,
  "42.0.3": 4949,
  "38.0.3": 71,
  "46.0.1": 4,
  "48.0.4": 6405,
  "48.0.0-beta.1": 6,
  "0.1.2": 6,
  "19.0.0-rc.3": 5,
  "15.0.0-rc.1": 5,
  "31.0.0-rc.2": 5,
  "33.0.0-rc.6": 5,
  "32.0.0-rc.0": 6
}