{
  "48.0.5": 2103,
  "32.0.0": 37,
  "1.0.0": 110,
  "30.0.0-rc.0": 5,
  "34.0.0-experiment.0": 5,
  "18.0.5": 13,
  "27.0.0-rc.0": 6,
  "18.0.9": 16,
  "15.1.2": 14,
  "25.1.2": 43,
  "48.0.16": 12850,
  "45.0.0-beta.2": 5,
  "42.0.0-beta.1": 5,
  "48.0.11": 6263,
  "49.0.0-alpha.8": 12,
  "37.0.6": 24,
  "43.0.0-alpha.2": 5,
  "49.0.2": 10588,
  "0.1.7": 13,
  "31.0.0-rc.3": 6,
  "48.0.8": 451,
  "47.0.12": 1836,
  "30.0.1": 26,
  "46.0.18": 137,
  "33.0.2": 22,
  "23.0.3": 11,
  "26.0.0": 22,
  "47.0.0-beta.2": 8,
  "34.0.0-experiment.3": 6,
  "18.0.1": 12,
  "48.0.18": 4579,
  "31.0.1": 18,
  "37.0.0": 21,
  "32.0.0-rc.1": 5,
  "33.0.0-alpha.web.1": 7,
  "31.0.6": 83,
  "32.0.4": 22,
  "0.1.6": 12,
  "46.0.12": 18,
  "33.0.7": 76,
  "49.0.0": 36371,
  "41.0.0-beta.2": 10,
  "44.0.2": 24,
  "33.0.6": 21,
  "14.0.0": 11,
  "48.0.3": 142,
  "47.0.3": 683,
  "34.0.2": 16,
  "42.0.0-beta.0": 5,
  "33.0.0-rc.6": 6,
  "19.0.1": 21,
  "24.0.2": 12,
  "37.0.10": 30,
  "39.0.2": 45,
  "43.0.1": 209,
  "32.0.5": 17,
  "20.0.0": 13,
  "48.0.0-beta.2": 103,
  "48.0.10": 7696,
  "38.0.10": 116,
  "0.1.3": 13,
  "30.0.0-rc.1": 5,
  "22.0.0": 12,
  "25.0.1": 17,
  "15.0.0": 14,
  "42.0.0-beta.2": 7,
  "48.0.13": 260,
  "32.0.2-rc.0": 5,
  "47.0.0-beta.5": 8,
  "21.0.0": 11,
  "37.0.8": 693,
  "22.0.1": 11,
  "47.0.0-beta.6": 8,
  "47.0.0-beta.7": 9,
  "20.0.1": 11,
  "38.0.5": 24,
  "43.0.4": 157,
  "17.0.0": 45,
  "24.1.1": 30,
  "34.0.0-rc.2": 5,
  "33.0.0-alpha.1": 5,
  "41.0.0-alpha.1": 6,
  "34.0.0-experiment.2": 6,
  "45.0.0-beta.9": 33,
  "46.0.9": 884,
  "46.0.14": 198,
  "43.0.0-beta.2": 5,
  "40.0.0-beta.4": 5,
  "47.0.5": 80,
  "45.0.0-beta.5": 6,
  "47.0.0-beta.8": 7,
  "46.0.6": 73,
  "47.0.13": 26870,
  "42.0.0-alpha.0": 6,
  "47.0.0-beta.4": 7,
  "40.0.0-beta.1": 5,
  "45.0.3": 103,
  "42.0.2": 17,
  "34.0.1": 109,
  "27.1.0": 42,
  "47.0.4": 34,
  "25.0.0": 29,
  "27.0.1": 45,
  "33.0.5": 21,
  "31.0.0-rc.1": 5,
  "33.0.0": 291,
  "33.0.0-rc.1": 6,
  "33.0.0-rc.2": 6,
  "34.0.0-experiment.8": 5,
  "43.0.0-beta.0": 6,
  "28.0.0-rc.0": 6,
  "15.0.1": 12,
  "32.0.2": 21,
  "17.0.0-rc.2": 1,
  "20.0.0-alpha.6": 1,
  "38.0.7-rc.0": 6,
  "41.0.0": 76,
  "46.0.20": 3352,
  "48.0.19": 127872,
  "44.0.0-beta.0": 5,
  "40.0.0-beta.2": 6,
  "29.0.0": 20,
  "30.0.0": 17,
  "49.0.0-beta.3": 77,
  "22.0.3": 12,
  "47.0.11": 320,
  "46.0.10": 1402,
  "34.0.4": 252,
  "33.0.0-rc.5": 5,
  "23.0.0-rc.0": 1,
  "45.0.0-beta.7": 7,
  "38.0.7": 18,
  "47.0.1": 30,
  "0.1.2": 11,
  "27.0.2-rc.1": 5,
  "38.0.8": 87,
  "40.0.1": 1247,
  "41.0.0-alpha.0": 6,
  "24.0.3": 16,
  "48.0.0-beta.1": 7,
  "47.0.9": 1736,
  "46.0.5": 19,
  "24.0.1": 13,
  "44.0.6": 27107,
  "42.0.5": 1391,
  "32.0.0-rc.3": 6,
  "0.1.4": 12,
  "46.0.13": 743,
  "46.0.0-alpha.2": 7,
  "48.0.9": 9227,
  "42.0.0-alpha.1": 7,
  "15.0.1-beta.0": 1,
  "19.0.0-rc.2": 1,
  "46.0.0-beta.7": 6,
  "40.0.0-beta.5": 6,
  "15.0.1-beta.1": 1,
  "40.0.0-alpha.0": 5,
  "37.0.7": 185,
  "20.0.3": 12,
  "23.0.4": 12,
  "44.0.5": 434,
  "45.0.2": 48,
  "40.0.0": 366,
  "23.0.1": 13,
  "22.0.4": 13,
  "38.0.9": 112,
  "20.0.5": 11,
  "46.0.16": 2736,
  "44.0.0-beta.2": 10,
  "20.0.2": 11,
  "44.0.0-beta.1": 5,
  "45.0.1": 47,
  "34.0.0-experiment.1": 6,
  "43.0.0-alpha.1": 6,
  "47.0.0-beta.3": 11,
  "44.0.4": 107,
  "46.0.3": 24,
  "42.0.3": 684,
  "46.0.1": 42,
  "45.0.8": 11286,
  "41.0.0-beta.1": 5,
  "33.0.0-rc.4": 6,
  "39.0.4": 273,
  "39.0.0": 16,
  "46.0.17": 932,
  "20.0.4": 11,
  "47.0.0-beta.1": 8,
  "46.0.0-beta.5": 6,
  "18.0.8": 12,
  "45.0.0": 630,
  "24.0.0": 11,
  "37.0.9": 26,
  "38.0.11": 403,
  "33.0.1": 17,
  "27.1.1": 61,
  "27.0.1-rc.0": 7,
  "31.0.0": 17,
  "45.0.0-beta.4": 6,
  "31.0.5": 196,
  "20.1.4": 20,
  "48.0.0-beta.0": 8,
  "23.0.5": 11,
  "34.0.0-experiment.4": 6,
  "20.0.0-alpha.4": 1,
  "21.0.1": 14,
  "28.0.1": 115,
  "43.0.0-beta.4": 6,
  "49.0.0-alpha.6": 19,
  "18.0.6": 12,
  "28.0.0-rc.2": 5,
  "48.0.7": 3694,
  "49.0.0-beta.2": 94,
  "49.0.0-alpha.4": 30,
  "29.0.0-rc.0": 6,
  "49.0.0-alpha.7": 15,
  "23.1.0": 16,
  "46.0.7": 78,
  "35.0.1": 696,
  "34.0.0-rc.0": 6,
  "35.0.0-rc.0": 6,
  "43.0.0-alpha.3": 5,
  "18.0.3": 21,
  "46.0.0-beta.3": 6,
  "48.0.6": 3203,
  "32.0.6": 629,
  "49.0.0-beta.5": 1082,
  "47.0.0-alpha.1": 14,
  "33.0.0-alpha.web.2": 6,
  "31.0.4": 29,
  "23.0.2": 12,
  "48.0.4": 3042,
  "49.0.1": 2697,
  "46.0.4": 20,
  "44.0.0-alpha.0": 5,
  "38.0.3": 23,
  "36.0.0-rc.0": 6,
  "37.0.12": 543,
  "46.0.0": 827,
  "34.0.0-rc.3": 6,
  "32.0.0-rc.0": 5,
  "49.0.0-beta.0": 35,
  "34.0.0-experiment.6": 5,
  "20.1.1": 12,
  "37.0.11": 87,
  "46.0.0-alpha.0": 6,
  "46.0.11": 19,
  "45.0.4": 427,
  "37.0.4": 22,
  "30.0.2": 71,
  "48.0.12": 992,
  "47.0.14": 40829,
  "43.0.0-beta.1": 5,
  "25.1.0": 16,
  "26.1.1": 21,
  "39.0.3": 129,
  "28.0.0-rc.1": 7,
  "45.0.0-beta.8": 5,
  "31.0.3": 16,
  "46.0.15": 563,
  "31.0.0-rc.2": 7,
  "46.0.0-beta.1": 6,
  "25.1.1": 21,
  "36.0.0": 207,
  "47.0.7": 490,
  "33.0.4": 16,
  "37.0.3": 52,
  "33.0.0-rc.3": 5,
  "38.0.6": 16,
  "34.0.0-experiment.7": 6,
  "46.0.0-alpha.1": 8,
  "47.0.6": 884,
  "49.0.0-alpha.9": 13,
  "49.0.0-alpha.10": 48,
  "47.0.0": 667,
  "42.0.0": 165,
  "15.1.3": 22,
  "47.0.10": 189,
  "23.0.6": 15,
  "29.0.0-rc.3": 5,
  "32.0.0-rc.4": 5,
  "41.0.0-beta.0": 5,
  "21.0.2": 14,
  "33.0.0-alpha.0": 6,
  "48.0.2": 27,
  "46.0.0-beta.2": 7,
  "18.0.2": 11,
  "23.0.0": 13,
  "49.0.0-alpha.1": 7,
  "48.0.14": 475,
  "45.0.0-beta.3": 7,
  "38.0.0": 19,
  "49.0.0-alpha.5": 9,
  "44.0.1": 68,
  "38.0.1": 17,
  "36.0.2": 839,
  "43.0.0-alpha.0": 5,
  "18.0.4-rc.0": 1,
  "18.0.0-rc.1": 1,
  "0.1.1": 14,
  "18.0.4": 12,
  "20.0.0-alpha.2": 1,
  "18.0.0-alpha.0": 1,
  "33.0.0-rc.0": 5,
  "46.0.21": 9856,
  "26.0.0-rc.2": 6,
  "40.0.0-beta.3": 6,
  "26.1.0": 17,
  "46.0.2": 178,
  "20.1.3": 12,
  "14.0.1": 14,
  "48.0.17": 16270,
  "37.0.1": 17,
  "46.0.19": 1782,
  "43.0.0": 386,
  "44.0.0": 333,
  "16.0.0-beta.0": 1,
  "23.0.0-rc.2": 1,
  "18.0.0-rc.2": 1,
  "34.0.0-experiment.5": 6,
  "24.0.0-rc.0": 1,
  "49.0.0-beta.1": 12,
  "41.0.0-beta.4": 6,
  "23.1.1": 31,
  "24.1.0": 16,
  "27.0.0": 23,
  "35.0.0": 90,
  "43.0.2": 105,
  "0.1.5": 13,
  "43.0.3": 477,
  "31.0.0-rc.0": 6,
  "46.0.0-alpha.3": 8,
  "49.0.0-beta.4": 403,
  "29.0.1": 36,
  "41.0.0-beta.3": 5,
  "29.0.0-rc.2": 5,
  "46.0.8": 227,
  "34.0.3": 68,
  "49.0.0-alpha.3": 203,
  "45.0.0-beta.1": 5,
  "38.0.2": 20,
  "48.0.20": 83316,
  "46.0.0-beta.6": 69,
  "32.0.0-rc.2": 6,
  "18.0.0": 11,
  "32.0.1": 27,
  "19.0.0": 11,
  "38.0.4": 23,
  "33.0.0-rc.7": 6,
  "33.0.3": 19,
  "48.0.1": 373,
  "46.0.0-beta.4": 7,
  "19.0.0-rc.1": 1,
  "34.0.0-rc.1": 5,
  "44.0.3": 132,
  "43.0.0-beta.3": 7,
  "39.0.1": 21,
  "28.0.0": 23,
  "20.0.0-alpha.0": 1,
  "45.0.5": 975,
  "15.0.0-rc.1": 1,
  "21.0.0-rc.3": 2,
  "24.0.0-rc.1": 1,
  "20.0.0-alpha.7": 1,
  "26.0.0-rc.1": 7,
  "42.0.4": 667,
  "22.1.0": 24,
  "22.0.2": 12,
  "43.0.5": 2897,
  "41.0.1": 1512,
  "49.0.0-alpha.2": 6,
  "45.0.7": 19,
  "48.0.15": 8531,
  "47.0.8": 3384,
  "45.0.6": 1827,
  "32.0.3": 19,
  "15.0.2": 16,
  "21.0.3": 22,
  "40.0.0-beta.0": 5,
  "27.0.2-rc.0": 5,
  "16.0.0": 14,
  "45.0.0-beta.6": 6,
  "26.0.0-rc.0": 5,
  "47.0.2": 23,
  "33.0.0-alpha.web.3": 7,
  "48.0.0": 2450,
  "14.0.2": 12,
  "33.0.0-alpha.web.0": 6,
  "31.0.2": 22,
  "37.0.2": 16,
  "36.0.1": 35,
  "29.0.1-rc.0": 5,
  "20.1.0": 11,
  "39.0.5": 875,
  "27.0.2": 25,
  "20.1.2": 11,
  "21.0.0-rc.4": 1,
  "42.0.1": 101,
  "37.0.5": 29,
  "25.0.0-rc.1": 1
}