{
  "43.0.0-beta.2": 3,
  "40.0.0-beta.4": 4,
  "45.0.0-beta.9": 5,
  "25.0.1": 4,
  "32.0.2-rc.0": 3,
  "44.0.2": 12,
  "19.0.0-rc.7": 2,
  "37.0.10": 7,
  "41.0.0-beta.2": 8,
  "33.0.6": 5,
  "0.1.3": 2,
  "48.0.10": 37225,
  "38.0.10": 107,
  "30.0.0-rc.1": 2,
  "22.0.0": 4,
  "42.0.0-beta.2": 3,
  "15.0.0": 3,
  "17.0.0-rc.3": 2,
  "20.0.0-alpha.1": 1,
  "42.0.0-beta.0": 3,
  "48.0.3": 124,
  "14.0.0": 2,
  "21.0.1": 2,
  "46.0.9": 1583,
  "46.0.14": 336,
  "47.0.5": 149,
  "38.0.5": 4,
  "20.0.1": 3,
  "29.0.0-rc.2": 4,
  "41.0.0-beta.3": 4,
  "32.0.0-rc.2": 4,
  "45.0.0-beta.1": 4,
  "21.0.0-rc.3": 2,
  "47.0.0-beta.2": 9,
  "31.0.1": 3,
  "34.0.0-experiment.3": 3,
  "47.0.10": 279,
  "32.0.0-rc.4": 3,
  "33.0.0-alpha.0": 3,
  "23.0.6": 6,
  "42.0.0": 129,
  "29.0.0-rc.3": 5,
  "18.0.2": 3,
  "21.0.0-rc.5": 2,
  "23.0.0": 1,
  "47.0.0-beta.7": 5,
  "47.0.0-beta.5": 8,
  "47.0.0-beta.6": 6,
  "37.0.8": 301,
  "21.0.0": 4,
  "22.0.1": 2,
  "36.0.2": 710,
  "38.0.1": 5,
  "44.0.1": 50,
  "43.0.0-alpha.0": 3,
  "45.0.0-beta.3": 3,
  "46.0.6": 86,
  "42.0.0-alpha.0": 3,
  "25.0.0-rc.0": 2,
  "30.0.0-rc.0": 4,
  "18.0.9": 4,
  "39.0.2": 69,
  "19.0.1": 5,
  "34.0.0-experiment.2": 3,
  "24.1.1": 6,
  "41.0.0-alpha.1": 3,
  "34.0.0-rc.2": 3,
  "17.0.0": 29,
  "47.0.0-beta.8": 35,
  "40.0.0-beta.1": 3,
  "21.0.3": 25,
  "45.0.6": 3276,
  "47.0.8": 8945,
  "45.0.7": 6,
  "19.0.0-alpha.0": 3,
  "40.0.0-beta.0": 3,
  "32.0.3": 3,
  "45.0.4": 778,
  "37.0.11": 14,
  "20.1.0": 3,
  "33.0.0-rc.6": 3,
  "15.0.0-rc.1": 2,
  "31.0.0-rc.2": 3,
  "33.0.4": 5,
  "19.0.0-rc.5": 2,
  "32.0.5": 6,
  "46.0.3": 27,
  "45.0.8": 19881,
  "16.0.0": 8,
  "15.0.2": 11,
  "20.0.0-alpha.5": 1,
  "27.0.2-rc.0": 3,
  "14.0.2": 3,
  "33.0.0-alpha.web.0": 3,
  "37.0.2": 5,
  "31.0.2": 5,
  "37.0.5": 3,
  "34.0.1": 115,
  "41.0.1": 1842,
  "22.0.2": 3,
  "21.0.0-alpha.2": 2,
  "22.1.0": 9,
  "43.0.5": 3097,
  "25.0.0-rc.1": 3,
  "21.0.0-rc.1": 2,
  "46.0.17": 3458,
  "47.0.0-beta.1": 8,
  "46.0.0-beta.5": 4,
  "18.0.8": 3,
  "33.0.0-rc.4": 3,
  "20.0.4": 1,
  "46.0.10": 2980,
  "30.0.0": 4,
  "22.0.3": 3,
  "29.0.0": 4,
  "47.0.2": 8,
  "26.0.0-rc.0": 3,
  "45.0.0-beta.6": 3,
  "0.1.1": 1,
  "27.1.1": 58,
  "33.0.1": 3,
  "48.0.0-beta.0": 12,
  "27.0.1-rc.0": 3,
  "23.0.5": 3,
  "45.0.0-beta.4": 2,
  "20.0.0-alpha.0": 3,
  "41.0.0-beta.0": 3,
  "29.0.1": 13,
  "46.0.0-beta.6": 39,
  "38.0.7": 5,
  "47.0.1": 54,
  "45.0.2": 498,
  "46.0.16": 7194,
  "22.0.4": 9,
  "23.0.4": 3,
  "20.0.2": 2,
  "20.0.5": 2,
  "33.0.0": 194,
  "33.0.0-rc.2": 3,
  "18.0.0-alpha.1": 2,
  "43.0.0-beta.0": 3,
  "33.0.0-rc.1": 2,
  "28.0.0-rc.0": 4,
  "44.0.4": 327,
  "41.0.0-beta.1": 3,
  "42.0.4": 618,
  "43.0.0-beta.1": 4,
  "47.0.14": 40965,
  "21.0.0-rc.0": 2,
  "48.0.2": 9,
  "46.0.0-beta.2": 3,
  "33.0.7": 36,
  "47.0.0-alpha.1": 46,
  "0.1.6": 2,
  "46.0.0-beta.3": 4,
  "48.0.7": 8529,
  "23.1.0": 5,
  "18.0.3": 17,
  "42.0.0-beta.1": 4,
  "46.0.5": 4,
  "47.0.9": 3131,
  "32.0.0-rc.3": 3,
  "0.1.4": 2,
  "24.0.1": 1,
  "36.0.1": 8,
  "42.0.1": 237,
  "46.0.12": 7,
  "39.0.5": 806,
  "27.0.2": 17,
  "33.0.0-alpha.web.1": 6,
  "21.0.0-rc.4": 2,
  "20.1.2": 2,
  "32.0.0-rc.1": 3,
  "29.0.1-rc.0": 3,
  "37.0.6": 12,
  "47.0.12": 3492,
  "48.0.0": 1218,
  "33.0.0-alpha.web.3": 5,
  "40.0.1": 1780,
  "38.0.8": 115,
  "24.0.3": 3,
  "41.0.0-alpha.0": 2,
  "27.0.2-rc.1": 4,
  "46.0.1": 16,
  "48.0.4": 5977,
  "42.0.3": 1038,
  "38.0.3": 7,
  "45.0.1": 57,
  "47.0.0-beta.3": 3,
  "20.0.0-alpha.3": 2,
  "18.0.0-rc.1": 3,
  "38.0.0": 10,
  "18.0.4-rc.0": 3,
  "28.0.1": 68,
  "18.0.6": 2,
  "46.0.11": 5,
  "20.1.1": 2,
  "46.0.0-alpha.0": 5,
  "34.0.0-experiment.6": 4,
  "46.0.0-alpha.3": 4,
  "43.0.2": 238,
  "35.0.0": 76,
  "20.0.0-alpha.7": 2,
  "31.0.0-rc.0": 3,
  "31.0.4": 4,
  "0.1.5": 1,
  "24.0.0-rc.0": 1,
  "33.0.0-alpha.web.2": 3,
  "24.1.0": 5,
  "37.0.4": 7,
  "30.0.2": 44,
  "48.0.12": 2695,
  "26.0.0-rc.2": 3,
  "46.0.21": 19108,
  "16.0.0-beta.0": 2,
  "40.0.0-beta.3": 3,
  "33.0.0-rc.0": 3,
  "20.1.3": 2,
  "26.1.0": 3,
  "14.0.1": 3,
  "44.0.0-beta.1": 3,
  "22.0.0-rc.0": 2,
  "17.0.0-rc.4": 2,
  "25.1.1": 3,
  "46.0.0-beta.7": 3,
  "32.0.0-rc.0": 2,
  "19.0.0-rc.3": 2,
  "20.1.4": 12,
  "31.0.5": 10,
  "46.0.15": 1141,
  "39.0.3": 170,
  "31.0.3": 4,
  "28.0.0-rc.1": 4,
  "26.1.1": 6,
  "22.0.0-rc.1": 2,
  "25.1.0": 3,
  "42.0.0-alpha.1": 3,
  "37.0.7": 125,
  "48.0.9": 23098,
  "40.0.0-alpha.0": 3,
  "15.0.1-beta.0": 3,
  "19.0.0-rc.2": 2,
  "34.0.0-experiment.0": 4,
  "32.0.0": 15,
  "48.0.5": 4190,
  "1.0.0": 167,
  "18.0.5": 2,
  "27.0.0-rc.0": 4,
  "0.1.2": 3,
  "48.0.0-beta.1": 6,
  "47.0.11": 879,
  "45.0.0-beta.5": 3,
  "40.0.0-beta.2": 3,
  "46.0.0-beta.4": 3,
  "19.0.0-rc.4": 2,
  "26.0.0-rc.1": 3,
  "43.0.0-alpha.3": 4,
  "34.0.0-rc.0": 4,
  "19.0.0": 2,
  "47.0.13": 47551,
  "47.0.0-beta.4": 4,
  "15.0.1-beta.1": 2,
  "38.0.6": 5,
  "34.0.0-experiment.7": 4,
  "28.0.0-rc.2": 3,
  "43.0.0-beta.3": 4,
  "43.0.0-beta.4": 3,
  "38.0.11": 410,
  "45.0.0": 1171,
  "37.0.9": 9,
  "24.0.0": 2,
  "27.0.1": 28,
  "46.0.0": 773,
  "46.0.4": 4,
  "23.0.2": 2,
  "18.0.0-rc.3": 2,
  "36.0.0-rc.0": 3,
  "44.0.0-alpha.0": 3,
  "45.0.3": 162,
  "47.0.4": 71,
  "42.0.2": 4,
  "27.1.0": 14,
  "46.0.20": 9432,
  "38.0.7-rc.0": 4,
  "17.0.0-rc.2": 1,
  "46.0.13": 990,
  "37.0.1": 3,
  "41.0.0-beta.4": 3,
  "21.0.0-alpha.0": 2,
  "33.0.0-alpha.1": 3,
  "43.0.4": 150,
  "18.0.4": 3,
  "20.0.0-alpha.2": 2,
  "41.0.0": 107,
  "32.0.2": 9,
  "20.0.0-alpha.6": 2,
  "18.0.0-alpha.0": 2,
  "44.0.0-beta.0": 3,
  "26.0.0": 7,
  "18.0.1": 2,
  "45.0.5": 1831,
  "47.0.7": 931,
  "37.0.12": 667,
  "46.0.0-beta.1": 3,
  "36.0.0": 103,
  "34.0.0-rc.3": 2,
  "37.0.3": 48,
  "47.0.6": 1383,
  "33.0.0-rc.3": 3,
  "46.0.0-alpha.1": 4,
  "45.0.0-beta.8": 4,
  "21.0.0-alpha.1": 2,
  "31.0.0-rc.3": 4,
  "18.0.0-rc.2": 3,
  "40.0.0-beta.5": 3,
  "46.0.0-alpha.2": 4,
  "20.0.3": 2,
  "25.0.0": 20,
  "19.0.0-rc.1": 2,
  "19.0.0-rc.0": 2,
  "24.0.2": 4,
  "48.0.0-beta.2": 57,
  "43.0.1": 233,
  "20.0.0": 2,
  "20.0.0-alpha.4": 2,
  "47.0.3": 1246,
  "34.0.2": 2,
  "32.0.4": 3,
  "31.0.6": 53,
  "33.0.0-rc.5": 3,
  "23.0.0-rc.2": 3,
  "34.0.0-experiment.4": 3,
  "31.0.0": 4,
  "15.1.2": 9,
  "44.0.3": 219,
  "34.0.0-rc.1": 3,
  "28.0.0": 17,
  "19.0.0-rc.6": 3,
  "40.0.0": 391,
  "34.0.3": 47,
  "38.0.9": 180,
  "44.0.0-beta.2": 8,
  "44.0.5": 547,
  "46.0.8": 205,
  "38.0.2": 5,
  "23.0.1": 2,
  "24.0.0-rc.1": 1,
  "47.0.0": 902,
  "15.1.3": 5,
  "34.0.4": 315,
  "21.0.2": 4,
  "25.1.2": 39,
  "45.0.0-beta.2": 5,
  "48.0.8": 1615,
  "30.0.1": 8,
  "46.0.18": 100,
  "23.0.3": 2,
  "33.0.2": 3,
  "32.0.6": 719,
  "48.0.6": 9356,
  "0.1.7": 3,
  "48.0.11": 155359,
  "43.0.0-alpha.2": 2,
  "43.0.3": 818,
  "23.1.1": 11,
  "34.0.0-experiment.5": 4,
  "27.0.0": 4,
  "48.0.1": 905,
  "33.0.0-rc.7": 5,
  "32.0.1": 9,
  "38.0.4": 7,
  "18.0.0": 3,
  "33.0.3": 4,
  "46.0.7": 119,
  "35.0.1": 1116,
  "29.0.0-rc.0": 4,
  "35.0.0-rc.0": 4,
  "43.0.0-alpha.1": 3,
  "34.0.0-experiment.1": 4,
  "43.0.0": 518,
  "46.0.2": 333,
  "46.0.19": 1753,
  "44.0.0": 456,
  "23.0.0-rc.1": 2,
  "39.0.1": 5,
  "16.0.0-rc.1": 2,
  "17.0.0-rc.1": 3,
  "23.0.0-rc.0": 3,
  "37.0.0": 9,
  "45.0.0-beta.7": 3,
  "42.0.5": 1900,
  "44.0.6": 26523,
  "33.0.5": 7,
  "34.0.0-experiment.8": 3,
  "15.0.1": 2,
  "31.0.0-rc.1": 3,
  "39.0.4": 222,
  "39.0.0": 26
}